pyhp/__init__.py
pyhp/__main__.py
pyhp/code_execution.py
pyhp/cookies.py
pyhp/file_processing.py
pyhp/hypertext_processing.py
pyhp/pyhp_flask.py
pyhp/pyhp_interface.py
pyhp/text_processing.py
python_hypertext_preprocessor-1.1.1.dist-info/LICENSE
python_hypertext_preprocessor-1.1.1.dist-info/METADATA
python_hypertext_preprocessor-1.1.1.dist-info/WHEEL
python_hypertext_preprocessor-1.1.1.dist-info/top_level.txt
python_hypertext_preprocessor-1.1.1.dist-info/RECORD
