Metadata-Version: 2.1
Name: python-hypertext-preprocessor
Version: 1.1.1
Summary: An HTML preprocessor for Python
Home-page: https://github.com/Benjymack/pyhp
Author: Benjy Smith
Classifier: Programming Language :: Python :: 3
Classifier: License :: OSI Approved :: MIT License
Classifier: Operating System :: OS Independent
License-File: LICENSE
Requires-Dist: Flask
